{
  "pages": [
    {
      "id": "ZxTn12Q",
      "grid": {
        "tiles": [
          {
            "tileType": "INSIGHT",
            "box": {
              "top": 0,
              "left": 0,
              "width": 5,
              "height": 3
            },
            "clickAction": "DO_NOTHING",
            "tileParams": {
              "showXAxis": true,
              "showYAxis": true,
              "showLegend": false,
              "showTooltips": true,
              "autoPlayAnimation": true
            },
            "autoLoad": true,
            "showTitle": "YES",
            "insightId": "YlqDa3W",
            "insightType": "chart",
            "displayMode": "INSIGHT",
            "resizeImageMode": "FIT_SIZE"
          },
          {
            "tileType": "INSIGHT",
            "box": {
              "top": -1,
              "left": -1,
              "width": 2,
              "height": 2
            },
            "clickAction": "OPEN_INSIGHT",
            "tileParams": {
              "showXAxis": true,
              "showYAxis": true,
              "showLegend": false,
              "showTooltips": true,
              "autoPlayAnimation": true
            },
            "autoLoad": true,
            "showTitle": "YES",
            "insightId": "HM8G9B8",
            "insightType": "chart",
            "displayMode": "INSIGHT",
            "resizeImageMode": "FIT_SIZE"
          }
        ]
      },
      "showTitle": false
    }
  ],
  "owner": "admin",
  "listed": false,
  "name": "Tabelogレビュー分析",
  "showGrid": true,
  "versionTag": {
    "versionNumber": 5,
    "lastModifiedBy": {
      "login": "admin"
    },
    "lastModifiedOn": 1623313854991
  },
  "creationTag": {
    "versionNumber": 0,
    "lastModifiedBy": {
      "login": "admin"
    },
    "lastModifiedOn": 1623313580811
  },
  "tags": [],
  "customFields": {},
  "checklists": {
    "checklists": []
  }
}